django_template_theming-0.8.2.dist-info/DESCRIPTION.rst
django_template_theming-0.8.2.dist-info/METADATA
django_template_theming-0.8.2.dist-info/RECORD
django_template_theming-0.8.2.dist-info/WHEEL
django_template_theming-0.8.2.dist-info/metadata.json
django_template_theming-0.8.2.dist-info/top_level.txt
theming/__init__.py
theming/admin.py
theming/middleware.py
theming/models.py
theming/template.py
theming/tests.py
theming/threadlocals.py
theming/views.py
theming/management/__init__.py
theming/management/commands/__init__.py
theming/management/commands/compress.py
theming/migrations/0001_initial.py
theming/migrations/0002_auto_20170508_0505.py
theming/migrations/__init__.py
